qualia_codegen_plugin_snn-2.5.0.dist-info/METADATA
qualia_codegen_plugin_snn-2.5.0.dist-info/WHEEL
qualia_codegen_plugin_snn-2.5.0.dist-info/entry_points.txt
qualia_codegen_plugin_snn-2.5.0.dist-info/licenses/LICENSE
qualia_codegen_plugin_snn/Converter.py
qualia_codegen_plugin_snn/__init__.py
qualia_codegen_plugin_snn/assets/.editorconfig
qualia_codegen_plugin_snn/assets/__init__.py
qualia_codegen_plugin_snn/assets/include/layers/if.hh
qualia_codegen_plugin_snn/assets/include/layers/lif.hh
qualia_codegen_plugin_snn/assets/include/layers/od_postprocess.hh
qualia_codegen_plugin_snn/assets/include/model.hh
qualia_codegen_plugin_snn/assets/layers/if.cc
qualia_codegen_plugin_snn/assets/layers/lif.cc
qualia_codegen_plugin_snn/assets/layers/od_postprocess.cc
qualia_codegen_plugin_snn/assets/layers/weights/if.cc
qualia_codegen_plugin_snn/assets/layers/weights/lif.cc
qualia_codegen_plugin_snn/assets/layers/weights/od_postprocess.cc
qualia_codegen_plugin_snn/assets/model.cc
qualia_codegen_plugin_snn/examples/Linux/.gitignore
qualia_codegen_plugin_snn/examples/Linux/CMakeLists.txt
qualia_codegen_plugin_snn/examples/Linux/README.md
qualia_codegen_plugin_snn/examples/Linux/SpikingNeuralNetwork.h
qualia_codegen_plugin_snn/examples/Linux/build.sh
qualia_codegen_plugin_snn/examples/Linux/main.cpp
qualia_codegen_plugin_snn/examples/Linux/single.cpp
qualia_codegen_plugin_snn/examples/NucleoL452REP/CMakeLists.txt
qualia_codegen_plugin_snn/examples/NucleoL452REP/Core/Inc/SpikingNeuralNetwork.h
qualia_codegen_plugin_snn/examples/NucleoL452REP/Core/Src/SpikingNeuralNetwork.cpp
qualia_codegen_plugin_snn/examples/NucleoL452REP/Core/Src/main_snn.c
qualia_codegen_plugin_snn/examples/__init__.py
qualia_codegen_plugin_snn/graph/TorchModelGraph.py
qualia_codegen_plugin_snn/graph/__init__.py
qualia_codegen_plugin_snn/graph/layers/TIfLayer.py
qualia_codegen_plugin_snn/graph/layers/TLifLayer.py
qualia_codegen_plugin_snn/graph/layers/TObjectDetectionPostProcessLayer.py
qualia_codegen_plugin_snn/graph/layers/__init__.py
qualia_codegen_plugin_snn/py.typed
qualia_codegen_plugin_snn-2.5.0.dist-info/RECORD
